nextcord/ext/listening/__init__.py
nextcord/ext/listening/enums.py
nextcord/ext/listening/gateway.py
nextcord/ext/listening/opus.py
nextcord/ext/listening/processing.py
nextcord/ext/listening/sink.py
nextcord/ext/listening/voice_client.py
nextcord_ext_listening-0.0.3.dist-info/LICENSE
nextcord_ext_listening-0.0.3.dist-info/METADATA
nextcord_ext_listening-0.0.3.dist-info/WHEEL
nextcord_ext_listening-0.0.3.dist-info/top_level.txt
nextcord_ext_listening-0.0.3.dist-info/RECORD
