Metadata-Version: 2.1
Name: nextcord-ext-listening
Version: 0.0.3
Summary: Voice receive extension for nextcord built on multiprocessing and designed to be flexible (port of Sheppsu/discord-ext-listening).
Home-page: https://github.com/RuslanUC/nextcord-ext-listening
Author: Sheppsu
License: MIT
Classifier: License :: OSI Approved :: MIT License
Classifier: Intended Audience :: Developers
Classifier: Natural Language :: English
Classifier: Operating System :: OS Independent
Classifier: Programming Language :: Python :: 3.8
Classifier: Programming Language :: Python :: 3.9
Classifier: Programming Language :: Python :: 3.10
Classifier: Programming Language :: Python :: 3.11
Classifier: Topic :: Multimedia :: Sound/Audio :: Capture/Recording
Requires-Python: >=3.8.0
License-File: LICENSE
